{
    "results": [
        {
            "ruleId": "html_skipnav_exists",
            "value": [
                "VIOLATION",
                "POTENTIAL"
            ],
            "path": {
                "dom": "/html[1]",
                "aria": "/document[1]"
            },
            "ruleTime": 0,
            "reasonId": "Potential_1",
            "message": "Verify there is a way to bypass blocks of content that are repeated on multiple Web pages",
            "messageArgs": [],
            "apiArgs": [],
            "bounds": {
                "left": 0,
                "top": 0,
                "height": 263,
                "width": 800
            },
            "snippet": "<html lang=\"en\">",
            "source": null,
            "category": "Accessibility",
            "level": "potentialviolation",
            "ignored": false,
            "help": "https://able.ibm.com/rules/archives/2026.05.19/doc/en-US/html_skipnav_exists.html#%7B%22message%22%3A%22Verify%20there%20is%20a%20way%20to%20bypass%20blocks%20of%20content%20that%20are%20repeated%20on%20multiple%20Web%20pages%22%2C%22snippet%22%3A%22%3Chtml%20lang%3D%5C%22en%5C%22%3E%22%2C%22value%22%3A%5B%22VIOLATION%22%2C%22POTENTIAL%22%5D%2C%22reasonId%22%3A%22Potential_1%22%2C%22ruleId%22%3A%22html_skipnav_exists%22%2C%22msgArgs%22%3A%5B%5D%7D"
        },
        {
            "ruleId": "aria_content_in_landmark",
            "value": [
                "VIOLATION",
                "FAIL"
            ],
            "path": {
                "dom": "/html[1]/body[1]/div[1]/div[1]/div[1]/a[1]",
                "aria": "/document[1]/link[1]"
            },
            "ruleTime": 1,
            "reasonId": "Fail_1",
            "message": "Content is not within a landmark element",
            "messageArgs": [],
            "apiArgs": [],
            "bounds": {
                "left": 266,
                "top": 8,
                "height": 18,
                "width": 10
            },
            "snippet": "<a class=\"close\" href=\"#\">",
            "source": null,
            "category": "Accessibility",
            "level": "violation",
            "ignored": false,
            "help": "https://able.ibm.com/rules/archives/2026.05.19/doc/en-US/aria_content_in_landmark.html#%7B%22message%22%3A%22Content%20is%20not%20within%20a%20landmark%20element%22%2C%22snippet%22%3A%22%3Ca%20class%3D%5C%22close%5C%22%20href%3D%5C%22%23%5C%22%3E%22%2C%22value%22%3A%5B%22VIOLATION%22%2C%22FAIL%22%5D%2C%22reasonId%22%3A%22Fail_1%22%2C%22ruleId%22%3A%22aria_content_in_landmark%22%2C%22msgArgs%22%3A%5B%5D%7D"
        },
        {
            "ruleId": "aria_content_in_landmark",
            "value": [
                "VIOLATION",
                "FAIL"
            ],
            "path": {
                "dom": "/html[1]/body[1]/div[2]/a[1]",
                "aria": "/document[1]/link[2]"
            },
            "ruleTime": 0,
            "reasonId": "Fail_1",
            "message": "Content is not within a landmark element",
            "messageArgs": [],
            "apiArgs": [],
            "bounds": {
                "left": 8,
                "top": 47,
                "height": 0,
                "width": 0
            },
            "snippet": "<a href=\"https://github.com/tourdedave/the-internet\">",
            "source": null,
            "category": "Accessibility",
            "level": "violation",
            "ignored": false,
            "help": "https://able.ibm.com/rules/archives/2026.05.19/doc/en-US/aria_content_in_landmark.html#%7B%22message%22%3A%22Content%20is%20not%20within%20a%20landmark%20element%22%2C%22snippet%22%3A%22%3Ca%20href%3D%5C%22https%3A%2F%2Fgithub.com%2Ftourdedave%2Fthe-internet%5C%22%3E%22%2C%22value%22%3A%5B%22VIOLATION%22%2C%22FAIL%22%5D%2C%22reasonId%22%3A%22Fail_1%22%2C%22ruleId%22%3A%22aria_content_in_landmark%22%2C%22msgArgs%22%3A%5B%5D%7D"
        },
        {
            "ruleId": "element_tabbable_visible",
            "value": [
                "VIOLATION",
                "POTENTIAL"
            ],
            "path": {
                "dom": "/html[1]/body[1]/div[2]/a[1]",
                "aria": "/document[1]/link[2]"
            },
            "ruleTime": 0,
            "reasonId": "potential_visible",
            "message": "Confirm the element should be tabbable and if so, it becomes visible when it has keyboard focus",
            "messageArgs": [],
            "apiArgs": [],
            "bounds": {
                "left": 8,
                "top": 47,
                "height": 0,
                "width": 0
            },
            "snippet": "<a href=\"https://github.com/tourdedave/the-internet\">",
            "source": null,
            "category": "Accessibility",
            "level": "potentialviolation",
            "ignored": false,
            "help": "https://able.ibm.com/rules/archives/2026.05.19/doc/en-US/element_tabbable_visible.html#%7B%22message%22%3A%22Confirm%20the%20element%20should%20be%20tabbable%20and%20if%20so%2C%20it%20becomes%20visible%20when%20it%20has%20keyboard%20focus%22%2C%22snippet%22%3A%22%3Ca%20href%3D%5C%22https%3A%2F%2Fgithub.com%2Ftourdedave%2Fthe-internet%5C%22%3E%22%2C%22value%22%3A%5B%22VIOLATION%22%2C%22POTENTIAL%22%5D%2C%22reasonId%22%3A%22potential_visible%22%2C%22ruleId%22%3A%22element_tabbable_visible%22%2C%22msgArgs%22%3A%5B%5D%7D"
        },
        {
            "ruleId": "aria_content_in_landmark",
            "value": [
                "VIOLATION",
                "FAIL"
            ],
            "path": {
                "dom": "/html[1]/body[1]/div[2]/div[1]/div[1]/h2[1]",
                "aria": "/document[1]/heading[1]"
            },
            "ruleTime": 0,
            "reasonId": "Fail_1",
            "message": "Content is not within a landmark element",
            "messageArgs": [],
            "apiArgs": [],
            "bounds": {
                "left": 8,
                "top": 47,
                "height": 28,
                "width": 784
            },
            "snippet": "<h2>",
            "source": null,
            "category": "Accessibility",
            "level": "violation",
            "ignored": false,
            "help": "https://able.ibm.com/rules/archives/2026.05.19/doc/en-US/aria_content_in_landmark.html#%7B%22message%22%3A%22Content%20is%20not%20within%20a%20landmark%20element%22%2C%22snippet%22%3A%22%3Ch2%3E%22%2C%22value%22%3A%5B%22VIOLATION%22%2C%22FAIL%22%5D%2C%22reasonId%22%3A%22Fail_1%22%2C%22ruleId%22%3A%22aria_content_in_landmark%22%2C%22msgArgs%22%3A%5B%5D%7D"
        },
        {
            "ruleId": "heading_markup_misuse",
            "value": [
                "VIOLATION",
                "POTENTIAL"
            ],
            "path": {
                "dom": "/html[1]/body[1]/div[2]/div[1]/div[1]/h4[1]",
                "aria": "/document[1]/heading[2]"
            },
            "ruleTime": 0,
            "reasonId": "Potential_1",
            "message": "Verify that the heading element is a genuine heading",
            "messageArgs": [],
            "apiArgs": [],
            "bounds": {
                "left": 8,
                "top": 96,
                "height": 37,
                "width": 784
            },
            "snippet": "<h4 class=\"subheader\">",
            "source": null,
            "category": "Accessibility",
            "level": "potentialviolation",
            "ignored": false,
            "help": "https://able.ibm.com/rules/archives/2026.05.19/doc/en-US/heading_markup_misuse.html#%7B%22message%22%3A%22Verify%20that%20the%20heading%20element%20is%20a%20genuine%20heading%22%2C%22snippet%22%3A%22%3Ch4%20class%3D%5C%22subheader%5C%22%3E%22%2C%22value%22%3A%5B%22VIOLATION%22%2C%22POTENTIAL%22%5D%2C%22reasonId%22%3A%22Potential_1%22%2C%22ruleId%22%3A%22heading_markup_misuse%22%2C%22msgArgs%22%3A%5B%5D%7D"
        },
        {
            "ruleId": "aria_content_in_landmark",
            "value": [
                "VIOLATION",
                "FAIL"
            ],
            "path": {
                "dom": "/html[1]/body[1]/div[3]/div[1]/div[1]/a[1]",
                "aria": "/document[1]/link[3]"
            },
            "ruleTime": 0,
            "reasonId": "Fail_1",
            "message": "Content is not within a landmark element",
            "messageArgs": [],
            "apiArgs": [],
            "bounds": {
                "left": 376,
                "top": 236,
                "height": 18,
                "width": 130
            },
            "snippet": "<a href=\"http://elementalselenium.com/\" target=\"_blank\">",
            "source": null,
            "category": "Accessibility",
            "level": "violation",
            "ignored": false,
            "help": "https://able.ibm.com/rules/archives/2026.05.19/doc/en-US/aria_content_in_landmark.html#%7B%22message%22%3A%22Content%20is%20not%20within%20a%20landmark%20element%22%2C%22snippet%22%3A%22%3Ca%20href%3D%5C%22http%3A%2F%2Felementalselenium.com%2F%5C%22%20target%3D%5C%22_blank%5C%22%3E%22%2C%22value%22%3A%5B%22VIOLATION%22%2C%22FAIL%22%5D%2C%22reasonId%22%3A%22Fail_1%22%2C%22ruleId%22%3A%22aria_content_in_landmark%22%2C%22msgArgs%22%3A%5B%5D%7D"
        }
    ],
    "numExecuted": 207,
    "ruleTime": 6,
    "nls": {
        "html_skipnav_exists": {
            "0": "Provide a way to bypass blocks of content that are repeated on multiple Web pages",
            "Potential_1": "Verify there is a way to bypass blocks of content that are repeated on multiple Web pages"
        },
        "aria_content_in_landmark": {
            "0": "All content must reside within an element with a landmark role",
            "Fail_1": "Content is not within a landmark element"
        },
        "element_tabbable_visible": {
            "0": "A tabbable element should be visible on the screen when it has keyboard focus",
            "potential_visible": "Confirm the element should be tabbable and if so, it becomes visible when it has keyboard focus"
        },
        "heading_markup_misuse": {
            "0": "Heading elements must not be used for presentation",
            "Potential_1": "Verify that the heading element is a genuine heading"
        }
    },
    "summary": {
        "counts": {
            "ignored": 0,
            "elements": 9,
            "elementsViolation": 4,
            "elementsViolationReview": 7,
            "violation": 4,
            "potentialviolation": 3,
            "recommendation": 0,
            "potentialrecommendation": 3,
            "manual": 1,
            "pass": 196
        },
        "scanTime": 27,
        "ruleArchive": "Latest Deployment (latest)",
        "policies": [
            "IBM_Accessibility"
        ],
        "reportLevels": [
            "violation",
            "potentialviolation"
        ],
        "startScan": 1779840107683,
        "URL": "data:text/html;charset=utf-8,%3C!doctype%20html%3E%0A%3Chtml%20lang%3D%22en%22%3E%0A%3Chead%3E%0A%20%20%3Cmeta%20charset%3D%22utf-8%22%3E%0A%20%20%3Ctitle%3EThe%20Internet%3C%2Ftitle%3E%0A%3C%2Fhead%3E%0A%3Cbody%3E%0A%3Cbody%3E%0A%20%20%20%20%3Cdiv%20class%3D%22row%22%3E%0A%20%20%20%20%20%20%3Cdiv%20id%3D%22flash-messages%22%20class%3D%22large-12%20columns%22%3E%0A%20%20%20%20%20%20%0A%20%20%20%20%20%20%20%20%0A%20%20%20%20%20%20%0A%20%20%20%20%20%20%20%20%0A%20%20%20%20%20%20%20%20%20%20%3Cdiv%20data-alert%3D%22%22%20id%3D%22flash%22%20class%3D%22flash%20error%22%3E%0A%20%20%20%20%20%20%20%20%20%20%20%20You%20must%20login%20to%20view%20the%20secure%20area!%0A%20%20%20%20%20%20%20%20%20%20%20%20%3Ca%20href%3D%22%23%22%20class%3D%22close%22%3E%C3%97%3C%2Fa%3E%0A%20%20%20%20%20%20%20%20%20%20%3C%2Fdiv%3E%0A%20%20%20%20%20%20%20%20%0A%20%20%20%20%20%20%0A%20%20%20%20%20%20%20%20%0A%20%20%20%20%20%20%0A%20%20%20%20%20%20%3C%2Fdiv%3E%0A%20%20%20%20%3C%2Fdiv%3E%0A%20%20%20%20%3Cdiv%20class%3D%22row%22%3E%0A%20%20%20%20%20%20%3Ca%20href%3D%22https%3A%2F%2Fgithub.com%2Ftourdedave%2Fthe-internet%22%3E%3Cimg%20style%3D%22position%3A%20absolute%3B%20top%3A%200%3B%20right%3A%200%3B%20border%3A%200%3B%22%20alt%3D%22Fork%20me%20on%20GitHub%22%3E%3C%2Fa%3E%0A%20%20%20%20%20%20%3Cdiv%20id%3D%22content%22%20class%3D%22large-12%20columns%22%3E%0A%20%20%20%20%20%20%20%20%3Cdiv%20class%3D%22example%22%3E%0A%20%20%3Ch2%3ELogin%20Page%3C%2Fh2%3E%0A%20%20%3Ch4%20class%3D%22subheader%22%3EThis%20is%20where%20you%20can%20log%20into%20the%20secure%20area.%20Enter%20%3Cem%3Etomsmith%3C%2Fem%3E%20for%20the%20username%20and%20%3Cem%3ESuperSecretPassword!%3C%2Fem%3E%20for%20the%20password.%20If%20the%20information%20is%20wrong%20you%20should%20see%20error%20messages.%3C%2Fh4%3E%0A%20%20%3Cform%20name%3D%22login%22%20id%3D%22login%22%20action%3D%22%2Fauthenticate%22%20method%3D%22post%22%3E%0A%20%20%20%20%20%3Cdiv%20class%3D%22row%22%3E%0A%20%20%20%20%20%20%3Cdiv%20class%3D%22large-6%20small-12%20columns%22%3E%0A%20%20%20%20%20%20%20%20%3Clabel%20for%3D%22username%22%3EUsername%3C%2Flabel%3E%0A%20%20%20%20%20%20%20%20%3Cinput%20type%3D%22text%22%20name%3D%22username%22%20id%3D%22username%22%3E%0A%20%20%20%20%20%20%3C%2Fdiv%3E%0A%20%20%20%20%3C%2Fdiv%3E%0A%20%20%20%20%3Cdiv%20class%3D%22row%22%3E%0A%20%20%20%20%20%20%3Cdiv%20class%3D%22large-6%20small-12%20columns%22%3E%0A%20%20%20%20%20%20%20%20%3Clabel%20for%3D%22password%22%3EPassword%3C%2Flabel%3E%0A%20%20%20%20%20%20%20%20%3Cinput%20type%3D%22password%22%20name%3D%22password%22%20id%3D%22password%22%3E%0A%20%20%20%20%20%20%3C%2Fdiv%3E%0A%20%20%20%20%3C%2Fdiv%3E%0A%20%20%20%20%20%20%3Cbutton%20class%3D%22radius%22%20type%3D%22submit%22%3E%3Ci%20class%3D%22fa%20fa-2x%20fa-sign-in%22%3E%20Login%3C%2Fi%3E%3C%2Fbutton%3E%0A%20%20%3C%2Fform%3E%0A%3C%2Fdiv%3E%0A%0A%20%20%20%20%20%20%3C%2Fdiv%3E%0A%20%20%20%20%3C%2Fdiv%3E%0A%20%20%20%20%3Cdiv%20id%3D%22page-footer%22%20class%3D%22row%22%3E%0A%20%20%20%20%20%20%3Cdiv%20class%3D%22large-4%20large-centered%20columns%22%3E%0A%20%20%20%20%20%20%20%20%3Chr%3E%0A%20%20%20%20%20%20%20%20%3Cdiv%20style%3D%22text-align%3A%20center%3B%22%3EPowered%20by%20%3Ca%20target%3D%22_blank%22%20href%3D%22http%3A%2F%2Felementalselenium.com%2F%22%3EElemental%20Selenium%3C%2Fa%3E%3C%2Fdiv%3E%0A%20%20%20%20%20%20%3C%2Fdiv%3E%0A%20%20%20%20%3C%2Fdiv%3E%0A%20%20%0A%0A%3C%2Fbody%3E%0A%3C%2Fbody%3E%0A%3C%2Fhtml%3E"
    },
    "scanID": "aeefdfe3-1f0b-45b2-b998-7479cc9b74a6",
    "toolID": "accessibility-checker-v4.0.10",
    "label": "the-internet.herokuapp.com-secure"
}